{
    "title": "Breadcrumbs",
    "tag": "ilw-breadcrumbs",
    "github": "https://github.com/web-illinois/ilw-breadcrumbs/",
    "type": "web component",
    "element-name": "ilw-breadcrumbs",
    "description": "Description for builder.",
    "version": "1.0.0-alpha",
    "date": "07/15/2024",
    "css": "https://dev.toolkit.illinois.edu/ilw-breadcrumbs/1.0.0-alpha/ilw-breadcrumbs.css",
    "js": "https://dev.toolkit.illinois.edu/ilw-breadcrumbs/1.0.0-alpha/ilw-breadcrumbs.js",
    "production": false,
    "notes": "",
    "parent-style": "",
    "samples": [
        {
            "name": "default",
            "description": "Default information",
            "text": "<a home=\"/\" href=\"/\">Home</a>\n    <a href=\"/academics\">Academics</a>\n    <a href=\"/academics/undergraduate\">Undergraduate programs</a>\n    <a href=\"\" current=\"\">Degree programs</a>"
        },
        {
            "name": "lastbreadcrumb",
            "description": "No link for last breadcrumb",
            "text": "<ilw-breadcrumbs>\n    <a home=\"/\" href=\"/\">Home</a>\n    <a href=\"/academics\">Academics</a>\n    <a href=\"/academics/undergraduate\">Undergraduate programs</a>\n    <span>Degree programs</span>\n</ilw-breadcrumbs>"
        }

    ],
    "attributes-fixed": [],
    "attributes-text": [],
    "attributes": [],
    "classes-fixed": [],
    "classes": [],
    "css-variables": []
}
